setup.py
jkj_probability_distributions/Binomialdistribution.py
jkj_probability_distributions/Gaussiandistribution.py
jkj_probability_distributions/Generaldistribution.py
jkj_probability_distributions/__init__.py
jkj_probability_distributions.egg-info/PKG-INFO
jkj_probability_distributions.egg-info/SOURCES.txt
jkj_probability_distributions.egg-info/dependency_links.txt
jkj_probability_distributions.egg-info/not-zip-safe
jkj_probability_distributions.egg-info/top_level.txt