Metadata-Version: 1.0
Name: jkj-probability-distributions
Version: 0.1
Summary: Gaussian and Binomial distributions
Home-page: UNKNOWN
Author: Jyothish James
Author-email: UNKNOWN
License: UNKNOWN
Platform: UNKNOWN
